{"data":{"pinned":{"edges":[{"node":{"id":"e22bb634-af21-5a80-8865-0cc846f1333b","frontmatter":{"title":"Getting Started"},"fields":{"slug":"/docs/getting-started/"}}},{"node":{"id":"9eba5a38-5c31-5a83-a53b-42dc939ccf7c","frontmatter":{"title":"Theme"},"fields":{"slug":"/docs/theme/"}}}]},"components":{"edges":[{"node":{"id":"f43fe554-5397-5f8f-8611-33de66e59e06","frontmatter":{"title":"Box"},"fields":{"slug":"/docs/box/"}}},{"node":{"id":"5c945c7f-e1c9-5d72-8b68-4b002c534b42","frontmatter":{"title":"Button"},"fields":{"slug":"/docs/button/"}}},{"node":{"id":"c15037ad-cfea-52b3-9ae3-2fa8b4bafce9","frontmatter":{"title":"Card"},"fields":{"slug":"/docs/card/"}}},{"node":{"id":"4fc1543b-0706-5806-b6fc-264a8be4102f","frontmatter":{"title":"CardLink"},"fields":{"slug":"/docs/card-link/"}}},{"node":{"id":"3046263a-27aa-546d-8262-f5d0996d6957","frontmatter":{"title":"Checkbox"},"fields":{"slug":"/docs/checkbox/"}}},{"node":{"id":"1da28e9a-fe37-5799-9305-1cd86699aace","frontmatter":{"title":"Chip"},"fields":{"slug":"/docs/chip/"}}},{"node":{"id":"056596f3-13c7-5163-8ff9-9db9e429facb","frontmatter":{"title":"Flex"},"fields":{"slug":"/docs/flex/"}}},{"node":{"id":"ffca924c-1a67-5f48-9202-b7933c19c9c3","frontmatter":{"title":"FormMessage"},"fields":{"slug":"/docs/form-message/"}}},{"node":{"id":"7fdab541-e605-540c-a884-92a29055186e","frontmatter":{"title":"Heading"},"fields":{"slug":"/docs/heading/"}}},{"node":{"id":"0468f921-702f-588c-8901-44941abc49d1","frontmatter":{"title":"Input"},"fields":{"slug":"/docs/input/"}}},{"node":{"id":"0907b32d-0d9b-5861-b27e-cf81afca29c2","frontmatter":{"title":"InputTags"},"fields":{"slug":"/docs/input-tags/"}}},{"node":{"id":"9b203c98-7724-5d77-94ec-18fb75be7196","frontmatter":{"title":"Loading"},"fields":{"slug":"/docs/Loading/"}}},{"node":{"id":"a0b05cc1-f719-58ab-a54b-53f2705f44ec","frontmatter":{"title":"Nav"},"fields":{"slug":"/docs/nav/"}}},{"node":{"id":"f55e0800-ef2b-5380-93c1-5e780410a072","frontmatter":{"title":"Radio"},"fields":{"slug":"/docs/radio/"}}},{"node":{"id":"dcd1cc56-6ebe-5109-b9ce-76552aaf3dd6","frontmatter":{"title":"Select"},"fields":{"slug":"/docs/select/"}}},{"node":{"id":"c3edd81a-e23a-547d-ab96-5b44a1e8629b","frontmatter":{"title":"SubNav"},"fields":{"slug":"/docs/subnav/"}}},{"node":{"id":"717ecd9b-b707-51f3-ab09-bdbe9e1aa3c1","frontmatter":{"title":"Table"},"fields":{"slug":"/docs/table/"}}},{"node":{"id":"c1eb6200-0b61-55be-ad04-484e2495140a","frontmatter":{"title":"Text"},"fields":{"slug":"/docs/text/"}}},{"node":{"id":"b0b832c4-65be-56c5-ae88-ca27a659763f","frontmatter":{"title":"ToggleButton"},"fields":{"slug":"/docs/toggle-button/"}}},{"node":{"id":"f68a38cc-572a-5f82-9d57-66398ed76573","frontmatter":{"title":"Tooltip"},"fields":{"slug":"/docs/tooltip/"}}}]}}}